{
  "years": {
    "2022": {
      "annual_PRENEI_Q": 65.3,
      "annual_PRELIQ_Q": 696.2,
      "annual_PE_Q": 229.5
    },
    "2023": {
      "annual_PRENEI_Q": 50.1,
      "annual_PRELIQ_Q": 788.8,
      "annual_PE_Q": 293.7
    },
    "2024": {
      "annual_PRENEI_Q": 59.1,
      "annual_PRELIQ_Q": 822.1,
      "annual_PE_Q": 346.3
    }
  },
  "months": {
    "2022-01": {
      "monthly_PRENEI_Q": 18.8,
      "monthly_PRELIQ_Q": 18.8,
      "monthly_PE_Q": 32.4
    },
    "2022-02": {
      "monthly_PRENEI_Q": 5.6,
      "monthly_PRELIQ_Q": 42.8,
      "monthly_PE_Q": 28.3
    },
    "2022-03": {
      "monthly_PRENEI_Q": 6.2,
      "monthly_PRELIQ_Q": 22.3,
      "monthly_PE_Q": -5.700000000000003
    },
    "2022-04": {
      "monthly_PRENEI_Q": 14.5,
      "monthly_PRELIQ_Q": 94.5,
      "monthly_PE_Q": 55.4
    },
    "2022-05": {
      "monthly_PRENEI_Q": 0.0,
      "monthly_PRELIQ_Q": 30.2,
      "monthly_PE_Q": -57.9
    },
    "2022-06": {
      "monthly_PRENEI_Q": 0.0,
      "monthly_PRELIQ_Q": 97.0,
      "monthly_PE_Q": 0.8999999999999986
    },
    "2022-07": {
      "monthly_PRENEI_Q": 0.0,
      "monthly_PRELIQ_Q": 14.0,
      "monthly_PE_Q": -62.199999999999996
    },
    "2022-08": {
      "monthly_PRENEI_Q": 0.0,
      "monthly_PRELIQ_Q": 52.4,
      "monthly_PE_Q": -3.299999999999999
    },
    "2022-09": {
      "monthly_PRENEI_Q": 0.0,
      "monthly_PRELIQ_Q": 102.8,
      "monthly_PE_Q": 54.0
    },
    "2022-10": {
      "monthly_PRENEI_Q": 0.0,
      "monthly_PRELIQ_Q": 87.3,
      "monthly_PE_Q": 51.4
    },
    "2022-11": {
      "monthly_PRENEI_Q": 0.0,
      "monthly_PRELIQ_Q": 82.3,
      "monthly_PE_Q": 68.0
    },
    "2022-12": {
      "monthly_PRENEI_Q": 20.200000000000003,
      "monthly_PRELIQ_Q": 51.8,
      "monthly_PE_Q": 68.2
    },
    "2023-01": {
      "monthly_PRENEI_Q": 17.0,
      "monthly_PRELIQ_Q": 40.800000000000004,
      "monthly_PE_Q": 48.9
    },
    "2023-02": {
      "monthly_PRENEI_Q": 1.6,
      "monthly_PRELIQ_Q": 6.7,
      "monthly_PE_Q": -1.5
    },
    "2023-03": {
      "monthly_PRENEI_Q": 2.8,
      "monthly_PRELIQ_Q": 90.8,
      "monthly_PE_Q": 64.5
    },
    "2023-04": {
      "monthly_PRENEI_Q": 0.3,
      "monthly_PRELIQ_Q": 73.7,
      "monthly_PE_Q": 34.7
    },
    "2023-05": {
      "monthly_PRENEI_Q": 0.0,
      "monthly_PRELIQ_Q": 39.800000000000004,
      "monthly_PE_Q": -35.7
    },
    "2023-06": {
      "monthly_PRENEI_Q": 0.0,
      "monthly_PRELIQ_Q": 68.8,
      "monthly_PE_Q": -27.499999999999996
    },
    "2023-07": {
      "monthly_PRENEI_Q": 0.0,
      "monthly_PRELIQ_Q": 92.5,
      "monthly_PE_Q": -10.1
    },
    "2023-08": {
      "monthly_PRENEI_Q": 0.0,
      "monthly_PRELIQ_Q": 67.6,
      "monthly_PE_Q": 0.8999999999999981
    },
    "2023-09": {
      "monthly_PRENEI_Q": 0.0,
      "monthly_PRELIQ_Q": 30.9,
      "monthly_PE_Q": -22.1
    },
    "2023-10": {
      "monthly_PRENEI_Q": 0.0,
      "monthly_PRELIQ_Q": 97.3,
      "monthly_PE_Q": 69.3
    },
    "2023-11": {
      "monthly_PRENEI_Q": 22.3,
      "monthly_PRELIQ_Q": 127.7,
      "monthly_PE_Q": 127.4
    },
    "2023-12": {
      "monthly_PRENEI_Q": 6.1,
      "monthly_PRELIQ_Q": 52.2,
      "monthly_PE_Q": 44.9
    },
    "2024-01": {
      "monthly_PRENEI_Q": 10.1,
      "monthly_PRELIQ_Q": 70.0,
      "monthly_PE_Q": 70.5
    },
    "2024-02": {
      "monthly_PRENEI_Q": 2.1,
      "monthly_PRELIQ_Q": 48.0,
      "monthly_PE_Q": 39.1
    },
    "2024-03": {
      "monthly_PRENEI_Q": 4.199999999999999,
      "monthly_PRELIQ_Q": 70.69999999999999,
      "monthly_PE_Q": 47.0
    },
    "2024-04": {
      "monthly_PRENEI_Q": 18.8,
      "monthly_PRELIQ_Q": 45.6,
      "monthly_PE_Q": 10.400000000000002
    },
    "2024-05": {
      "monthly_PRENEI_Q": 0.0,
      "monthly_PRELIQ_Q": 115.1,
      "monthly_PE_Q": 46.4
    },
    "2024-06": {
      "monthly_PRENEI_Q": 0.0,
      "monthly_PRELIQ_Q": 90.0,
      "monthly_PE_Q": 2.8999999999999995
    },
    "2024-07": {
      "monthly_PRENEI_Q": 0.0,
      "monthly_PRELIQ_Q": 72.8,
      "monthly_PE_Q": -33.1
    },
    "2024-08": {
      "monthly_PRENEI_Q": 0.0,
      "monthly_PRELIQ_Q": 45.4,
      "monthly_PE_Q": -35.199999999999996
    },
    "2024-09": {
      "monthly_PRENEI_Q": 0.0,
      "monthly_PRELIQ_Q": 126.3,
      "monthly_PE_Q": 75.0
    },
    "2024-10": {
      "monthly_PRENEI_Q": 0.0,
      "monthly_PRELIQ_Q": 103.19999999999999,
      "monthly_PE_Q": 77.89999999999999
    },
    "2024-11": {
      "monthly_PRENEI_Q": 23.9,
      "monthly_PRELIQ_Q": 34.8,
      "monthly_PE_Q": 45.4
    },
    "2024-12": {
      "monthly_PRENEI_Q": 0.0,
      "monthly_PRELIQ_Q": 0.2,
      "monthly_PE_Q": 0.0
    }
  }
}