{
  "years": {
    "2020": {
      "annual_PRELIQ_Q": 633.9
    },
    "2021": {
      "annual_PRELIQ_Q": 609.9
    },
    "2022": {
      "annual_PRELIQ_Q": 467.1
    },
    "2023": {
      "annual_PRELIQ_Q": 769.3
    },
    "2024": {
      "annual_PRELIQ_Q": 717.0
    }
  },
  "months": {
    "2020-01": {
      "monthly_PRELIQ_Q": 43.9
    },
    "2020-02": {
      "monthly_PRELIQ_Q": 52.6
    },
    "2020-03": {
      "monthly_PRELIQ_Q": 70.7
    },
    "2020-04": {
      "monthly_PRELIQ_Q": 47.7
    },
    "2020-05": {
      "monthly_PRELIQ_Q": 53.6
    },
    "2020-06": {
      "monthly_PRELIQ_Q": 62.199999999999996
    },
    "2020-07": {
      "monthly_PRELIQ_Q": 6.7
    },
    "2020-08": {
      "monthly_PRELIQ_Q": 45.9
    },
    "2020-09": {
      "monthly_PRELIQ_Q": 49.2
    },
    "2020-10": {
      "monthly_PRELIQ_Q": 94.1
    },
    "2020-11": {
      "monthly_PRELIQ_Q": 22.3
    },
    "2020-12": {
      "monthly_PRELIQ_Q": 85.0
    },
    "2021-01": {
      "monthly_PRELIQ_Q": 74.0
    },
    "2021-02": {
      "monthly_PRELIQ_Q": 46.9
    },
    "2021-03": {
      "monthly_PRELIQ_Q": 15.0
    },
    "2021-04": {
      "monthly_PRELIQ_Q": 14.799999999999999
    },
    "2021-05": {
      "monthly_PRELIQ_Q": 75.3
    },
    "2021-06": {
      "monthly_PRELIQ_Q": 113.5
    },
    "2021-07": {
      "monthly_PRELIQ_Q": 46.9
    },
    "2021-08": {
      "monthly_PRELIQ_Q": 23.2
    },
    "2021-09": {
      "monthly_PRELIQ_Q": 26.0
    },
    "2021-10": {
      "monthly_PRELIQ_Q": 58.0
    },
    "2021-11": {
      "monthly_PRELIQ_Q": 36.8
    },
    "2021-12": {
      "monthly_PRELIQ_Q": 79.5
    },
    "2022-01": {
      "monthly_PRELIQ_Q": 36.1
    },
    "2022-02": {
      "monthly_PRELIQ_Q": 20.4
    },
    "2022-03": {
      "monthly_PRELIQ_Q": 19.8
    },
    "2022-04": {
      "monthly_PRELIQ_Q": 40.9
    },
    "2022-05": {
      "monthly_PRELIQ_Q": 11.600000000000001
    },
    "2022-06": {
      "monthly_PRELIQ_Q": 55.8
    },
    "2022-07": {
      "monthly_PRELIQ_Q": 8.5
    },
    "2022-08": {
      "monthly_PRELIQ_Q": 44.9
    },
    "2022-09": {
      "monthly_PRELIQ_Q": 63.50000000000001
    },
    "2022-10": {
      "monthly_PRELIQ_Q": 36.1
    },
    "2022-11": {
      "monthly_PRELIQ_Q": 75.9
    },
    "2022-12": {
      "monthly_PRELIQ_Q": 53.6
    },
    "2023-01": {
      "monthly_PRELIQ_Q": 68.9
    },
    "2023-02": {
      "monthly_PRELIQ_Q": 25.5
    },
    "2023-03": {
      "monthly_PRELIQ_Q": 84.1
    },
    "2023-04": {
      "monthly_PRELIQ_Q": 38.7
    },
    "2023-05": {
      "monthly_PRELIQ_Q": 49.4
    },
    "2023-06": {
      "monthly_PRELIQ_Q": 71.2
    },
    "2023-07": {
      "monthly_PRELIQ_Q": 38.9
    },
    "2023-08": {
      "monthly_PRELIQ_Q": 43.400000000000006
    },
    "2023-09": {
      "monthly_PRELIQ_Q": 88.39999999999999
    },
    "2023-10": {
      "monthly_PRELIQ_Q": 122.9
    },
    "2023-11": {
      "monthly_PRELIQ_Q": 82.10000000000001
    },
    "2023-12": {
      "monthly_PRELIQ_Q": 55.8
    },
    "2024-01": {
      "monthly_PRELIQ_Q": 55.4
    },
    "2024-02": {
      "monthly_PRELIQ_Q": 69.8
    },
    "2024-03": {
      "monthly_PRELIQ_Q": 82.8
    },
    "2024-04": {
      "monthly_PRELIQ_Q": 38.0
    },
    "2024-05": {
      "monthly_PRELIQ_Q": 88.4
    },
    "2024-06": {
      "monthly_PRELIQ_Q": 73.3
    },
    "2024-07": {
      "monthly_PRELIQ_Q": 38.6
    },
    "2024-08": {
      "monthly_PRELIQ_Q": 52.0
    },
    "2024-09": {
      "monthly_PRELIQ_Q": 70.0
    },
    "2024-10": {
      "monthly_PRELIQ_Q": 89.39999999999999
    },
    "2024-11": {
      "monthly_PRELIQ_Q": 57.2
    },
    "2024-12": {
      "monthly_PRELIQ_Q": 2.1
    }
  }
}