{"97420":{"nom":"Sainte-Suzanne","priceAc_value":0.75,"priceAc_year":2023.0,"priceEp_value":1.35,"priceEp_year":2023,"priceTotal_value":2.1,"priceTotal_year":2023.0},"97421":{"nom":"Salazie","priceAc_value":null,"priceAc_year":null,"priceEp_value":2.7,"priceEp_year":2023,"priceTotal_value":null,"priceTotal_year":null},"97422":{"nom":"Le Tampon","priceAc_value":1.52,"priceAc_year":2023.0,"priceEp_value":1.22,"priceEp_year":2023,"priceTotal_value":2.74,"priceTotal_year":2023.0},"97423":{"nom":"Les Trois-Bassins","priceAc_value":1.69,"priceAc_year":2023.0,"priceEp_value":1.45,"priceEp_year":2023,"priceTotal_value":3.14,"priceTotal_year":2023.0},"97424":{"nom":"Cilaos","priceAc_value":0.37,"priceAc_year":2023.0,"priceEp_value":1.64,"priceEp_year":2023,"priceTotal_value":2.01,"priceTotal_year":2023.0},"97401":{"nom":"Les Avirons","priceAc_value":1.05,"priceAc_year":2023.0,"priceEp_value":2.19,"priceEp_year":2023,"priceTotal_value":3.24,"priceTotal_year":2023.0},"97402":{"nom":"Bras-Panon","priceAc_value":1.62,"priceAc_year":2023.0,"priceEp_value":0.98,"priceEp_year":2023,"priceTotal_value":2.6,"priceTotal_year":2023.0},"97403":{"nom":"Entre-Deux","priceAc_value":1.52,"priceAc_year":2023.0,"priceEp_value":1.22,"priceEp_year":2023,"priceTotal_value":2.74,"priceTotal_year":2023.0},"97404":{"nom":"L' Étang-Salé","priceAc_value":2.14,"priceAc_year":2023.0,"priceEp_value":1.17,"priceEp_year":2023,"priceTotal_value":3.31,"priceTotal_year":2023.0},"97405":{"nom":"Petite-Île","priceAc_value":null,"priceAc_year":null,"priceEp_value":2.53,"priceEp_year":2023,"priceTotal_value":null,"priceTotal_year":null},"97406":{"nom":"La Plaine-des-Palmistes","priceAc_value":null,"priceAc_year":null,"priceEp_value":1.46,"priceEp_year":2023,"priceTotal_value":null,"priceTotal_year":null},"97407":{"nom":"Le Port","priceAc_value":1.63,"priceAc_year":2023.0,"priceEp_value":0.79,"priceEp_year":2023,"priceTotal_value":2.42,"priceTotal_year":2023.0},"97408":{"nom":"La Possession","priceAc_value":1.72,"priceAc_year":2023.0,"priceEp_value":1.75,"priceEp_year":2023,"priceTotal_value":3.47,"priceTotal_year":2023.0},"97409":{"nom":"Saint-André","priceAc_value":1.3,"priceAc_year":2023.0,"priceEp_value":1.27,"priceEp_year":2023,"priceTotal_value":2.57,"priceTotal_year":2023.0},"97410":{"nom":"Saint-Benoît","priceAc_value":2.07,"priceAc_year":2023.0,"priceEp_value":1.68,"priceEp_year":2023,"priceTotal_value":3.75,"priceTotal_year":2023.0},"97411":{"nom":"Saint-Denis","priceAc_value":0.75,"priceAc_year":2023.0,"priceEp_value":1.42,"priceEp_year":2023,"priceTotal_value":2.17,"priceTotal_year":2023.0},"97412":{"nom":"Saint-Joseph","priceAc_value":1.52,"priceAc_year":2023.0,"priceEp_value":1.22,"priceEp_year":2023,"priceTotal_value":2.74,"priceTotal_year":2023.0},"97413":{"nom":"Saint-Leu","priceAc_value":1.6,"priceAc_year":2023.0,"priceEp_value":1.54,"priceEp_year":2023,"priceTotal_value":3.14,"priceTotal_year":2023.0},"97414":{"nom":"Saint-Louis","priceAc_value":1.9,"priceAc_year":2023.0,"priceEp_value":1.27,"priceEp_year":2023,"priceTotal_value":3.17,"priceTotal_year":2023.0},"97415":{"nom":"Saint-Paul","priceAc_value":1.51,"priceAc_year":2023.0,"priceEp_value":1.22,"priceEp_year":2023,"priceTotal_value":2.73,"priceTotal_year":2023.0},"97416":{"nom":"Saint-Pierre","priceAc_value":1.37,"priceAc_year":2023.0,"priceEp_value":1.17,"priceEp_year":2023,"priceTotal_value":2.54,"priceTotal_year":2023.0},"97417":{"nom":"Saint-Philippe","priceAc_value":1.52,"priceAc_year":2023.0,"priceEp_value":1.22,"priceEp_year":2023,"priceTotal_value":2.74,"priceTotal_year":2023.0},"97418":{"nom":"Sainte-Marie","priceAc_value":0.75,"priceAc_year":2023.0,"priceEp_value":1.74,"priceEp_year":2023,"priceTotal_value":2.49,"priceTotal_year":2023.0},"97419":{"nom":"Sainte-Rose","priceAc_value":0.55,"priceAc_year":2023.0,"priceEp_value":1.85,"priceEp_year":2023,"priceTotal_value":2.4,"priceTotal_year":2023.0}}